{"huggan--selfie2anime": {"description": "", "citation": "", "homepage": "", "license": "", "features": {"imageA": {"decode": true, "id": null, "_type": "Image"}, "imageB": {"decode": true, "id": null, "_type": "Image"}}, "post_processed": null, "supervised_keys": null, "task_templates": null, "builder_name": null, "config_name": null, "version": null, "splits": {"train": {"name": "train", "num_bytes": 406412493.6, "num_examples": 3400, "dataset_name": "selfie2anime"}, "test": {"name": "test", "num_bytes": 11720296.0, "num_examples": 100, "dataset_name": "selfie2anime"}}, "download_checksums": null, "download_size": 411418872, "post_processing_size": null, "dataset_size": 418132789.6, "size_in_bytes": 829551661.6}}